pystacho/__init__.py
pystacho/config.py
pystacho/database.py
pystacho/helper.py
pystacho/logger.py
pystacho/model.py
pystacho/query_builder.py
pystacho/relation.py
pystacho/adapters/__init__.py
pystacho/adapters/mysql.py
pystacho/adapters/postgres.py
pystacho/adapters/sqlite.py
pystacho-0.1.6.dist-info/LICENSE
pystacho-0.1.6.dist-info/METADATA
pystacho-0.1.6.dist-info/WHEEL
pystacho-0.1.6.dist-info/top_level.txt
pystacho-0.1.6.dist-info/RECORD
