Metadata-Version: 2.1
Name: pystacho
Version: 0.1.6
Summary: A simple ORM for Python, inspired by ActiveRecord, of Rails framework.
Home-page: https://github.com/paul-ot/pystacho-orm
Author: Paul Marclay
Author-email: paul.eduardo.marclay@gmail.com
Classifier: Programming Language :: Python :: 3
Classifier: License :: OSI Approved :: MIT License
Classifier: Operating System :: OS Independent
Requires-Python: >=3.6
License-File: LICENSE
Requires-Dist: inflect
Requires-Dist: inflection
Requires-Dist: pyyaml
Requires-Dist: colorama
